multiplier.v
//*****Booth multiplier*****
module multiplier(p,a,b);
	input[3:0] a;
	input[3:0] b;
	output[7:0] p;
	reg[7:0] s1,s2,s3,s4;
	reg[7:0] p;
	always @(*) begin
		if ({a[0],1'b0}==2'b00) s1=8'b00000000;
		else if ({a[0],1'b0}==2'b01) s1={4'b0000,b};
		else if ({a[0],1'b0}==2'b10) begin
			if (b==4'b0000) s1=8'b00000000;
			else s1={4'b1111,~b+4'b0001};
		end
		else if ({a[0],1'b0}==2'b11) s1={4'b0000,4'b0000};
	end
	always @(*) begin
		if ({a[1],a[0]}==2'b00) s2=8'b00000000;
		else if ({a[1],a[0]}==2'b01) s2={3'b000,b,1'b0};
		else if ({a[1],a[0]}==2'b10) begin
			if (b==4'b0000) s2=8'b00000000;
			else s2={3'b111,~b+4'b0001,1'b0};
		end
		else if ({a[1],a[0]}==2'b11) s2={4'b0000,4'b0000};
	end
	always @(*) begin
		if ({a[2],a[1]}==2'b00) s3=8'b00000000;
		else if ({a[2],a[1]}==2'b01) s3={2'b00,b,2'b00};
		else if ({a[2],a[1]}==2'b10) begin
			if (b==4'b0000) s3=8'b00000000;
			else s3={2'b11,~b+4'b0001,2'b00};
		end
		else if ({a[2],a[1]}==2'b11) s3={4'b0000,4'b0000};
	end
	always @(*) begin
		if ({a[3],a[2]}==2'b00) s4=8'b00000000;
		else if ({a[3],a[2]}==2'b01) s4={1'b0,b,3'b000};
		else if ({a[3],a[2]}==2'b10) begin
			if (b==4'b000) s4=8'b00000000;
			else s4={1'b1,~b+4'b0001,3'b000};
		end
		else if ({a[3],a[2]}==2'b11) s4={4'b0000,4'b0000};
	end
	always @(*) begin
		p=s1+s2+s3+s4;
		
	end

endmodule

module tb_multiplier();
	reg signed[3:0] a;
	reg signed[3:0] b;
	wire signed[7:0] p;
multiplier U1(.a(a),.b(b),.p(p));
integer i;
integer j;
integer count;
initial count =0;
initial begin
	for (i=-8;i<=7;i=i+1) begin
		for (j=0;j<=15;j=j+1) begin
			a=i;
			b=j;
			#10;
			if (i*j==p) count=count+1;
			else $display("Error : %4d x %4d = %4d",a,b,p);
			#90;
		end
	end
	$display("success = %4d , errors = %4d",count,count-256);
	$finish;
end
initial begin
	$dumpfile("database.vcd");
	$dumpvars(0,tb_multiplier);
end
//always @(*) $display("%4d x %4d = %4d",a,b,p);
endmodule

database.vcd
$date
	Tue Apr 30 23:43:56 2024
$end
$version
	Icarus Verilog
$end
$timescale
	1s
$end
$scope module tb_multiplier $end
$var wire 8 ! p [7:0] $end
$var reg 4 " a [3:0] $end
$var reg 4 # b [3:0] $end
$var integer 32 $ count [31:0] $end
$var integer 32 % i [31:0] $end
$var integer 32 & j [31:0] $end
$scope module U1 $end
$var wire 4 ' a [3:0] $end
$var wire 4 ( b [3:0] $end
$var reg 8 ) p [7:0] $end
$var reg 8 * s1 [7:0] $end
$var reg 8 + s2 [7:0] $end
$var reg 8 , s3 [7:0] $end
$var reg 8 - s4 [7:0] $end
$upscope $end
$upscope $end
$enddefinitions $end
#0
$dumpvars
b0 -
b0 ,
b0 +
b0 *
b0 )
b0 (
b1000 '
b0 &
b11111111111111111111111111111000 %
b0 $
b0 #
b1000 "
b0 !
$end
#10
b1 $
#100
b11111000 !
b11111000 )
b11111000 -
b1 #
b1 (
b1 &
#110
b10 $
#200
b11110000 !
b11110000 )
b11110000 -
b10 #
b10 (
b10 &
#210
b11 $
#300
b11101000 !
b11101000 )
b11101000 -
b11 #
b11 (
b11 &
#310
b100 $
#400
b11100000 !
b11100000 )
b11100000 -
b100 #
b100 (
b100 &
#410
b101 $
#500
b11011000 !
b11011000 )
b11011000 -
b101 #
b101 (
b101 &
#510
b110 $
#600
b11010000 !
b11010000 )
b11010000 -
b110 #
b110 (
b110 &
#610
b111 $
#700
b11001000 !
b11001000 )
b11001000 -
b111 #
b111 (
b111 &
#710
b1000 $
#800
b11000000 !
b11000000 )
b11000000 -
b1000 #
b1000 (
b1000 &
#810
b1001 $
#900
b10111000 !
b10111000 )
b10111000 -
b1001 #
b1001 (
b1001 &
#910
b1010 $
#1000
b10110000 !
b10110000 )
b10110000 -
b1010 #
b1010 (
b1010 &
#1010
b1011 $
#1100
b10101000 !
b10101000 )
b10101000 -
b1011 #
b1011 (
b1011 &
#1110
b1100 $
#1200
b10100000 !
b10100000 )
b10100000 -
b1100 #
b1100 (
b1100 &
#1210
b1101 $
#1300
b10011000 !
b10011000 )
b10011000 -
b1101 #
b1101 (
b1101 &
#1310
b1110 $
#1400
b10010000 !
b10010000 )
b10010000 -
b1110 #
b1110 (
b1110 &
#1410
b1111 $
#1500
b10001000 !
b10001000 )
b10001000 -
b1111 #
b1111 (
b1111 &
#1510
b10000 $
#1600
b0 !
b0 )
b0 -
b0 #
b0 (
b1001 "
b1001 '
b11111111111111111111111111111001 %
b0 &
#1610
b10001 $
#1700
b11111001 !
b11111001 )
b11111111 *
b10 +
b11111000 -
b1 #
b1 (
b1 &
#1710
b10010 $
#1800
b11110010 !
b11110010 )
b11110000 -
b100 +
b11111110 *
b10 #
b10 (
b10 &
#1810
b10011 $
#1900
b11101011 !
b11101011 )
b11111101 *
b110 +
b11101000 -
b11 #
b11 (
b11 &
#1910
b10100 $
#2000
b11100100 !
b11100100 )
b11100000 -
b1000 +
b11111100 *
b100 #
b100 (
b100 &
#2010
b10101 $
#2100
b11011101 !
b11011101 )
b11111011 *
b1010 +
b11011000 -
b101 #
b101 (
b101 &
#2110
b10110 $
#2200
b11010110 !
b11010110 )
b11010000 -
b1100 +
b11111010 *
b110 #
b110 (
b110 &
#2210
b10111 $
#2300
b11001111 !
b11001111 )
b11111001 *
b1110 +
b11001000 -
b111 #
b111 (
b111 &
#2310
b11000 $
#2400
b11001000 !
b11001000 )
b11000000 -
b10000 +
b11111000 *
b1000 #
b1000 (
b1000 &
#2410
b11001 $
#2500
b11000001 !
b11000001 )
b11110111 *
b10010 +
b10111000 -
b1001 #
b1001 (
b1001 &
#2510
b11010 $
#2600
b10111010 !
b10111010 )
b10110000 -
b10100 +
b11110110 *
b1010 #
b1010 (
b1010 &
#2610
b11011 $
#2700
b10110011 !
b10110011 )
b11110101 *
b10110 +
b10101000 -
b1011 #
b1011 (
b1011 &
#2710
b11100 $
#2800
b10101100 !
b10101100 )
b10100000 -
b11000 +
b11110100 *
b1100 #
b1100 (
b1100 &
#2810
b11101 $
#2900
b10100101 !
b10100101 )
b11110011 *
b11010 +
b10011000 -
b1101 #
b1101 (
b1101 &
#2910
b11110 $
#3000
b10011110 !
b10011110 )
b10010000 -
b11100 +
b11110010 *
b1110 #
b1110 (
b1110 &
#3010
b11111 $
#3100
b10010111 !
b10010111 )
b11110001 *
b11110 +
b10001000 -
b1111 #
b1111 (
b1111 &
#3110
b100000 $
#3200
b0 !
b0 )
b0 -
b0 +
b0 *
b0 #
b0 (
b1010 "
b1010 '
b11111111111111111111111111111010 %
b0 &
#3210
b100001 $
#3300
b11111010 !
b11111010 )
b11111110 +
b100 ,
b11111000 -
b1 #
b1 (
b1 &
#3310
b100010 $
#3400
b11110100 !
b11110100 )
b11110000 -
b1000 ,
b11111100 +
b10 #
b10 (
b10 &
#3410
b100011 $
#3500
b11101110 !
b11101110 )
b11111010 +
b1100 ,
b11101000 -
b11 #
b11 (
b11 &
#3510
b100100 $
#3600
b11101000 !
b11101000 )
b11100000 -
b10000 ,
b11111000 +
b100 #
b100 (
b100 &
#3610
b100101 $
#3700
b11100010 !
b11100010 )
b11110110 +
b10100 ,
b11011000 -
b101 #
b101 (
b101 &
#3710
b100110 $
#3800
b11011100 !
b11011100 )
b11010000 -
b11000 ,
b11110100 +
b110 #
b110 (
b110 &
#3810
b100111 $
#3900
b11010110 !
b11010110 )
b11110010 +
b11100 ,
b11001000 -
b111 #
b111 (
b111 &
#3910
b101000 $
#4000
b11010000 !
b11010000 )
b11000000 -
b100000 ,
b11110000 +
b1000 #
b1000 (
b1000 &
#4010
b101001 $
#4100
b11001010 !
b11001010 )
b11101110 +
b100100 ,
b10111000 -
b1001 #
b1001 (
b1001 &
#4110
b101010 $
#4200
b11000100 !
b11000100 )
b10110000 -
b101000 ,
b11101100 +
b1010 #
b1010 (
b1010 &
#4210
b101011 $
#4300
b10111110 !
b10111110 )
b11101010 +
b101100 ,
b10101000 -
b1011 #
b1011 (
b1011 &
#4310
b101100 $
#4400
b10111000 !
b10111000 )
b10100000 -
b110000 ,
b11101000 +
b1100 #
b1100 (
b1100 &
#4410
b101101 $
#4500
b10110010 !
b10110010 )
b11100110 +
b110100 ,
b10011000 -
b1101 #
b1101 (
b1101 &
#4510
b101110 $
#4600
b10101100 !
b10101100 )
b10010000 -
b111000 ,
b11100100 +
b1110 #
b1110 (
b1110 &
#4610
b101111 $
#4700
b10100110 !
b10100110 )
b11100010 +
b111100 ,
b10001000 -
b1111 #
b1111 (
b1111 &
#4710
b110000 $
#4800
b0 !
b0 )
b0 -
b0 ,
b0 +
b0 #
b0 (
b1011 "
b1011 '
b11111111111111111111111111111011 %
b0 &
#4810
b110001 $
#4900
b11111011 !
b11111011 )
b11111111 *
b100 ,
b11111000 -
b1 #
b1 (
b1 &
#4910
b110010 $
#5000
b11110110 !
b11110110 )
b11110000 -
b1000 ,
b11111110 *
b10 #
b10 (
b10 &
#5010
b110011 $
#5100
b11110001 !
b11110001 )
b11111101 *
b1100 ,
b11101000 -
b11 #
b11 (
b11 &
#5110
b110100 $
#5200
b11101100 !
b11101100 )
b11100000 -
b10000 ,
b11111100 *
b100 #
b100 (
b100 &
#5210
b110101 $
#5300
b11100111 !
b11100111 )
b11111011 *
b10100 ,
b11011000 -
b101 #
b101 (
b101 &
#5310
b110110 $
#5400
b11100010 !
b11100010 )
b11010000 -
b11000 ,
b11111010 *
b110 #
b110 (
b110 &
#5410
b110111 $
#5500
b11011101 !
b11011101 )
b11111001 *
b11100 ,
b11001000 -
b111 #
b111 (
b111 &
#5510
b111000 $
#5600
b11011000 !
b11011000 )
b11000000 -
b100000 ,
b11111000 *
b1000 #
b1000 (
b1000 &
#5610
b111001 $
#5700
b11010011 !
b11010011 )
b11110111 *
b100100 ,
b10111000 -
b1001 #
b1001 (
b1001 &
#5710
b111010 $
#5800
b11001110 !
b11001110 )
b10110000 -
b101000 ,
b11110110 *
b1010 #
b1010 (
b1010 &
#5810
b111011 $
#5900
b11001001 !
b11001001 )
b11110101 *
b101100 ,
b10101000 -
b1011 #
b1011 (
b1011 &
#5910
b111100 $
#6000
b11000100 !
b11000100 )
b10100000 -
b110000 ,
b11110100 *
b1100 #
b1100 (
b1100 &
#6010
b111101 $
#6100
b10111111 !
b10111111 )
b11110011 *
b110100 ,
b10011000 -
b1101 #
b1101 (
b1101 &
#6110
b111110 $
#6200
b10111010 !
b10111010 )
b10010000 -
b111000 ,
b11110010 *
b1110 #
b1110 (
b1110 &
#6210
b111111 $
#6300
b10110101 !
b10110101 )
b11110001 *
b111100 ,
b10001000 -
b1111 #
b1111 (
b1111 &
#6310
b1000000 $
#6400
b0 !
b0 )
b0 -
b0 ,
b0 *
b0 #
b0 (
b1100 "
b1100 '
b11111111111111111111111111111100 %
b0 &
#6410
b1000001 $
#6500
b11111100 !
b11111100 )
b11111100 ,
b1 #
b1 (
b1 &
#6510
b1000010 $
#6600
b11111000 !
b11111000 )
b11111000 ,
b10 #
b10 (
b10 &
#6610
b1000011 $
#6700
b11110100 !
b11110100 )
b11110100 ,
b11 #
b11 (
b11 &
#6710
b1000100 $
#6800
b11110000 !
b11110000 )
b11110000 ,
b100 #
b100 (
b100 &
#6810
b1000101 $
#6900
b11101100 !
b11101100 )
b11101100 ,
b101 #
b101 (
b101 &
#6910
b1000110 $
#7000
b11101000 !
b11101000 )
b11101000 ,
b110 #
b110 (
b110 &
#7010
b1000111 $
#7100
b11100100 !
b11100100 )
b11100100 ,
b111 #
b111 (
b111 &
#7110
b1001000 $
#7200
b11100000 !
b11100000 )
b11100000 ,
b1000 #
b1000 (
b1000 &
#7210
b1001001 $
#7300
b11011100 !
b11011100 )
b11011100 ,
b1001 #
b1001 (
b1001 &
#7310
b1001010 $
#7400
b11011000 !
b11011000 )
b11011000 ,
b1010 #
b1010 (
b1010 &
#7410
b1001011 $
#7500
b11010100 !
b11010100 )
b11010100 ,
b1011 #
b1011 (
b1011 &
#7510
b1001100 $
#7600
b11010000 !
b11010000 )
b11010000 ,
b1100 #
b1100 (
b1100 &
#7610
b1001101 $
#7700
b11001100 !
b11001100 )
b11001100 ,
b1101 #
b1101 (
b1101 &
#7710
b1001110 $
#7800
b11001000 !
b11001000 )
b11001000 ,
b1110 #
b1110 (
b1110 &
#7810
b1001111 $
#7900
b11000100 !
b11000100 )
b11000100 ,
b1111 #
b1111 (
b1111 &
#7910
b1010000 $
#8000
b0 !
b0 )
b0 ,
b0 #
b0 (
b1101 "
b1101 '
b11111111111111111111111111111101 %
b0 &
#8010
b1010001 $
#8100
b11111101 !
b11111101 )
b11111111 *
b10 +
b11111100 ,
b1 #
b1 (
b1 &
#8110
b1010010 $
#8200
b11111010 !
b11111010 )
b11111000 ,
b100 +
b11111110 *
b10 #
b10 (
b10 &
#8210
b1010011 $
#8300
b11110111 !
b11110111 )
b11111101 *
b110 +
b11110100 ,
b11 #
b11 (
b11 &
#8310
b1010100 $
#8400
b11110100 !
b11110100 )
b11110000 ,
b1000 +
b11111100 *
b100 #
b100 (
b100 &
#8410
b1010101 $
#8500
b11110001 !
b11110001 )
b11111011 *
b1010 +
b11101100 ,
b101 #
b101 (
b101 &
#8510
b1010110 $
#8600
b11101110 !
b11101110 )
b11101000 ,
b1100 +
b11111010 *
b110 #
b110 (
b110 &
#8610
b1010111 $
#8700
b11101011 !
b11101011 )
b11111001 *
b1110 +
b11100100 ,
b111 #
b111 (
b111 &
#8710
b1011000 $
#8800
b11101000 !
b11101000 )
b11100000 ,
b10000 +
b11111000 *
b1000 #
b1000 (
b1000 &
#8810
b1011001 $
#8900
b11100101 !
b11100101 )
b11110111 *
b10010 +
b11011100 ,
b1001 #
b1001 (
b1001 &
#8910
b1011010 $
#9000
b11100010 !
b11100010 )
b11011000 ,
b10100 +
b11110110 *
b1010 #
b1010 (
b1010 &
#9010
b1011011 $
#9100
b11011111 !
b11011111 )
b11110101 *
b10110 +
b11010100 ,
b1011 #
b1011 (
b1011 &
#9110
b1011100 $
#9200
b11011100 !
b11011100 )
b11010000 ,
b11000 +
b11110100 *
b1100 #
b1100 (
b1100 &
#9210
b1011101 $
#9300
b11011001 !
b11011001 )
b11110011 *
b11010 +
b11001100 ,
b1101 #
b1101 (
b1101 &
#9310
b1011110 $
#9400
b11010110 !
b11010110 )
b11001000 ,
b11100 +
b11110010 *
b1110 #
b1110 (
b1110 &
#9410
b1011111 $
#9500
b11010011 !
b11010011 )
b11110001 *
b11110 +
b11000100 ,
b1111 #
b1111 (
b1111 &
#9510
b1100000 $
#9600
b0 !
b0 )
b0 ,
b0 +
b0 *
b0 #
b0 (
b1110 "
b1110 '
b11111111111111111111111111111110 %
b0 &
#9610
b1100001 $
#9700
b11111110 !
b11111110 )
b11111110 +
b1 #
b1 (
b1 &
#9710
b1100010 $
#9800
b11111100 !
b11111100 )
b11111100 +
b10 #
b10 (
b10 &
#9810
b1100011 $
#9900
b11111010 !
b11111010 )
b11111010 +
b11 #
b11 (
b11 &
#9910
b1100100 $
#10000
b11111000 !
b11111000 )
b11111000 +
b100 #
b100 (
b100 &
#10010
b1100101 $
#10100
b11110110 !
b11110110 )
b11110110 +
b101 #
b101 (
b101 &
#10110
b1100110 $
#10200
b11110100 !
b11110100 )
b11110100 +
b110 #
b110 (
b110 &
#10210
b1100111 $
#10300
b11110010 !
b11110010 )
b11110010 +
b111 #
b111 (
b111 &
#10310
b1101000 $
#10400
b11110000 !
b11110000 )
b11110000 +
b1000 #
b1000 (
b1000 &
#10410
b1101001 $
#10500
b11101110 !
b11101110 )
b11101110 +
b1001 #
b1001 (
b1001 &
#10510
b1101010 $
#10600
b11101100 !
b11101100 )
b11101100 +
b1010 #
b1010 (
b1010 &
#10610
b1101011 $
#10700
b11101010 !
b11101010 )
b11101010 +
b1011 #
b1011 (
b1011 &
#10710
b1101100 $
#10800
b11101000 !
b11101000 )
b11101000 +
b1100 #
b1100 (
b1100 &
#10810
b1101101 $
#10900
b11100110 !
b11100110 )
b11100110 +
b1101 #
b1101 (
b1101 &
#10910
b1101110 $
#11000
b11100100 !
b11100100 )
b11100100 +
b1110 #
b1110 (
b1110 &
#11010
b1101111 $
#11100
b11100010 !
b11100010 )
b11100010 +
b1111 #
b1111 (
b1111 &
#11110
b1110000 $
#11200
b0 !
b0 )
b0 +
b0 #
b0 (
b1111 "
b1111 '
b11111111111111111111111111111111 %
b0 &
#11210
b1110001 $
#11300
b11111111 !
b11111111 )
b11111111 *
b1 #
b1 (
b1 &
#11310
b1110010 $
#11400
b11111110 !
b11111110 )
b11111110 *
b10 #
b10 (
b10 &
#11410
b1110011 $
#11500
b11111101 !
b11111101 )
b11111101 *
b11 #
b11 (
b11 &
#11510
b1110100 $
#11600
b11111100 !
b11111100 )
b11111100 *
b100 #
b100 (
b100 &
#11610
b1110101 $
#11700
b11111011 !
b11111011 )
b11111011 *
b101 #
b101 (
b101 &
#11710
b1110110 $
#11800
b11111010 !
b11111010 )
b11111010 *
b110 #
b110 (
b110 &
#11810
b1110111 $
#11900
b11111001 !
b11111001 )
b11111001 *
b111 #
b111 (
b111 &
#11910
b1111000 $
#12000
b11111000 !
b11111000 )
b11111000 *
b1000 #
b1000 (
b1000 &
#12010
b1111001 $
#12100
b11110111 !
b11110111 )
b11110111 *
b1001 #
b1001 (
b1001 &
#12110
b1111010 $
#12200
b11110110 !
b11110110 )
b11110110 *
b1010 #
b1010 (
b1010 &
#12210
b1111011 $
#12300
b11110101 !
b11110101 )
b11110101 *
b1011 #
b1011 (
b1011 &
#12310
b1111100 $
#12400
b11110100 !
b11110100 )
b11110100 *
b1100 #
b1100 (
b1100 &
#12410
b1111101 $
#12500
b11110011 !
b11110011 )
b11110011 *
b1101 #
b1101 (
b1101 &
#12510
b1111110 $
#12600
b11110010 !
b11110010 )
b11110010 *
b1110 #
b1110 (
b1110 &
#12610
b1111111 $
#12700
b11110001 !
b11110001 )
b11110001 *
b1111 #
b1111 (
b1111 &
#12710
b10000000 $
#12800
b0 !
b0 )
b0 *
b0 #
b0 (
b0 "
b0 '
b0 %
b0 &
#12810
b10000001 $
#12900
b1 #
b1 (
b1 &
#12910
b10000010 $
#13000
b10 #
b10 (
b10 &
#13010
b10000011 $
#13100
b11 #
b11 (
b11 &
#13110
b10000100 $
#13200
b100 #
b100 (
b100 &
#13210
b10000101 $
#13300
b101 #
b101 (
b101 &
#13310
b10000110 $
#13400
b110 #
b110 (
b110 &
#13410
b10000111 $
#13500
b111 #
b111 (
b111 &
#13510
b10001000 $
#13600
b1000 #
b1000 (
b1000 &
#13610
b10001001 $
#13700
b1001 #
b1001 (
b1001 &
#13710
b10001010 $
#13800
b1010 #
b1010 (
b1010 &
#13810
b10001011 $
#13900
b1011 #
b1011 (
b1011 &
#13910
b10001100 $
#14000
b1100 #
b1100 (
b1100 &
#14010
b10001101 $
#14100
b1101 #
b1101 (
b1101 &
#14110
b10001110 $
#14200
b1110 #
b1110 (
b1110 &
#14210
b10001111 $
#14300
b1111 #
b1111 (
b1111 &
#14310
b10010000 $
#14400
b0 #
b0 (
b1 "
b1 '
b1 %
b0 &
#14410
b10010001 $
#14500
b1 !
b1 )
b11111111 *
b10 +
b1 #
b1 (
b1 &
#14510
b10010010 $
#14600
b10 !
b10 )
b100 +
b11111110 *
b10 #
b10 (
b10 &
#14610
b10010011 $
#14700
b11 !
b11 )
b11111101 *
b110 +
b11 #
b11 (
b11 &
#14710
b10010100 $
#14800
b100 !
b100 )
b1000 +
b11111100 *
b100 #
b100 (
b100 &
#14810
b10010101 $
#14900
b101 !
b101 )
b11111011 *
b1010 +
b101 #
b101 (
b101 &
#14910
b10010110 $
#15000
b110 !
b110 )
b1100 +
b11111010 *
b110 #
b110 (
b110 &
#15010
b10010111 $
#15100
b111 !
b111 )
b11111001 *
b1110 +
b111 #
b111 (
b111 &
#15110
b10011000 $
#15200
b1000 !
b1000 )
b10000 +
b11111000 *
b1000 #
b1000 (
b1000 &
#15210
b10011001 $
#15300
b1001 !
b1001 )
b11110111 *
b10010 +
b1001 #
b1001 (
b1001 &
#15310
b10011010 $
#15400
b1010 !
b1010 )
b10100 +
b11110110 *
b1010 #
b1010 (
b1010 &
#15410
b10011011 $
#15500
b1011 !
b1011 )
b11110101 *
b10110 +
b1011 #
b1011 (
b1011 &
#15510
b10011100 $
#15600
b1100 !
b1100 )
b11000 +
b11110100 *
b1100 #
b1100 (
b1100 &
#15610
b10011101 $
#15700
b1101 !
b1101 )
b11110011 *
b11010 +
b1101 #
b1101 (
b1101 &
#15710
b10011110 $
#15800
b1110 !
b1110 )
b11100 +
b11110010 *
b1110 #
b1110 (
b1110 &
#15810
b10011111 $
#15900
b1111 !
b1111 )
b11110001 *
b11110 +
b1111 #
b1111 (
b1111 &
#15910
b10100000 $
#16000
b0 !
b0 )
b0 +
b0 *
b0 #
b0 (
b10 "
b10 '
b10 %
b0 &
#16010
b10100001 $
#16100
b10 !
b10 )
b11111110 +
b100 ,
b1 #
b1 (
b1 &
#16110
b10100010 $
#16200
b100 !
b100 )
b1000 ,
b11111100 +
b10 #
b10 (
b10 &
#16210
b10100011 $
#16300
b110 !
b110 )
b11111010 +
b1100 ,
b11 #
b11 (
b11 &
#16310
b10100100 $
#16400
b1000 !
b1000 )
b10000 ,
b11111000 +
b100 #
b100 (
b100 &
#16410
b10100101 $
#16500
b1010 !
b1010 )
b11110110 +
b10100 ,
b101 #
b101 (
b101 &
#16510
b10100110 $
#16600
b1100 !
b1100 )
b11000 ,
b11110100 +
b110 #
b110 (
b110 &
#16610
b10100111 $
#16700
b1110 !
b1110 )
b11110010 +
b11100 ,
b111 #
b111 (
b111 &
#16710
b10101000 $
#16800
b10000 !
b10000 )
b100000 ,
b11110000 +
b1000 #
b1000 (
b1000 &
#16810
b10101001 $
#16900
b10010 !
b10010 )
b11101110 +
b100100 ,
b1001 #
b1001 (
b1001 &
#16910
b10101010 $
#17000
b10100 !
b10100 )
b101000 ,
b11101100 +
b1010 #
b1010 (
b1010 &
#17010
b10101011 $
#17100
b10110 !
b10110 )
b11101010 +
b101100 ,
b1011 #
b1011 (
b1011 &
#17110
b10101100 $
#17200
b11000 !
b11000 )
b110000 ,
b11101000 +
b1100 #
b1100 (
b1100 &
#17210
b10101101 $
#17300
b11010 !
b11010 )
b11100110 +
b110100 ,
b1101 #
b1101 (
b1101 &
#17310
b10101110 $
#17400
b11100 !
b11100 )
b111000 ,
b11100100 +
b1110 #
b1110 (
b1110 &
#17410
b10101111 $
#17500
b11110 !
b11110 )
b11100010 +
b111100 ,
b1111 #
b1111 (
b1111 &
#17510
b10110000 $
#17600
b0 !
b0 )
b0 ,
b0 +
b0 #
b0 (
b11 "
b11 '
b11 %
b0 &
#17610
b10110001 $
#17700
b11 !
b11 )
b11111111 *
b100 ,
b1 #
b1 (
b1 &
#17710
b10110010 $
#17800
b110 !
b110 )
b1000 ,
b11111110 *
b10 #
b10 (
b10 &
#17810
b10110011 $
#17900
b1001 !
b1001 )
b11111101 *
b1100 ,
b11 #
b11 (
b11 &
#17910
b10110100 $
#18000
b1100 !
b1100 )
b10000 ,
b11111100 *
b100 #
b100 (
b100 &
#18010
b10110101 $
#18100
b1111 !
b1111 )
b11111011 *
b10100 ,
b101 #
b101 (
b101 &
#18110
b10110110 $
#18200
b10010 !
b10010 )
b11000 ,
b11111010 *
b110 #
b110 (
b110 &
#18210
b10110111 $
#18300
b10101 !
b10101 )
b11111001 *
b11100 ,
b111 #
b111 (
b111 &
#18310
b10111000 $
#18400
b11000 !
b11000 )
b100000 ,
b11111000 *
b1000 #
b1000 (
b1000 &
#18410
b10111001 $
#18500
b11011 !
b11011 )
b11110111 *
b100100 ,
b1001 #
b1001 (
b1001 &
#18510
b10111010 $
#18600
b11110 !
b11110 )
b101000 ,
b11110110 *
b1010 #
b1010 (
b1010 &
#18610
b10111011 $
#18700
b100001 !
b100001 )
b11110101 *
b101100 ,
b1011 #
b1011 (
b1011 &
#18710
b10111100 $
#18800
b100100 !
b100100 )
b110000 ,
b11110100 *
b1100 #
b1100 (
b1100 &
#18810
b10111101 $
#18900
b100111 !
b100111 )
b11110011 *
b110100 ,
b1101 #
b1101 (
b1101 &
#18910
b10111110 $
#19000
b101010 !
b101010 )
b111000 ,
b11110010 *
b1110 #
b1110 (
b1110 &
#19010
b10111111 $
#19100
b101101 !
b101101 )
b11110001 *
b111100 ,
b1111 #
b1111 (
b1111 &
#19110
b11000000 $
#19200
b0 !
b0 )
b0 ,
b0 *
b0 #
b0 (
b100 "
b100 '
b100 %
b0 &
#19210
b11000001 $
#19300
b100 !
b100 )
b11111100 ,
b1000 -
b1 #
b1 (
b1 &
#19310
b11000010 $
#19400
b1000 !
b1000 )
b10000 -
b11111000 ,
b10 #
b10 (
b10 &
#19410
b11000011 $
#19500
b1100 !
b1100 )
b11110100 ,
b11000 -
b11 #
b11 (
b11 &
#19510
b11000100 $
#19600
b10000 !
b10000 )
b100000 -
b11110000 ,
b100 #
b100 (
b100 &
#19610
b11000101 $
#19700
b10100 !
b10100 )
b11101100 ,
b101000 -
b101 #
b101 (
b101 &
#19710
b11000110 $
#19800
b11000 !
b11000 )
b110000 -
b11101000 ,
b110 #
b110 (
b110 &
#19810
b11000111 $
#19900
b11100 !
b11100 )
b11100100 ,
b111000 -
b111 #
b111 (
b111 &
#19910
b11001000 $
#20000
b100000 !
b100000 )
b1000000 -
b11100000 ,
b1000 #
b1000 (
b1000 &
#20010
b11001001 $
#20100
b100100 !
b100100 )
b11011100 ,
b1001000 -
b1001 #
b1001 (
b1001 &
#20110
b11001010 $
#20200
b101000 !
b101000 )
b1010000 -
b11011000 ,
b1010 #
b1010 (
b1010 &
#20210
b11001011 $
#20300
b101100 !
b101100 )
b11010100 ,
b1011000 -
b1011 #
b1011 (
b1011 &
#20310
b11001100 $
#20400
b110000 !
b110000 )
b1100000 -
b11010000 ,
b1100 #
b1100 (
b1100 &
#20410
b11001101 $
#20500
b110100 !
b110100 )
b11001100 ,
b1101000 -
b1101 #
b1101 (
b1101 &
#20510
b11001110 $
#20600
b111000 !
b111000 )
b1110000 -
b11001000 ,
b1110 #
b1110 (
b1110 &
#20610
b11001111 $
#20700
b111100 !
b111100 )
b11000100 ,
b1111000 -
b1111 #
b1111 (
b1111 &
#20710
b11010000 $
#20800
b0 !
b0 )
b0 -
b0 ,
b0 #
b0 (
b101 "
b101 '
b101 %
b0 &
#20810
b11010001 $
#20900
b101 !
b101 )
b11111111 *
b10 +
b11111100 ,
b1000 -
b1 #
b1 (
b1 &
#20910
b11010010 $
#21000
b1010 !
b1010 )
b10000 -
b11111000 ,
b100 +
b11111110 *
b10 #
b10 (
b10 &
#21010
b11010011 $
#21100
b1111 !
b1111 )
b11111101 *
b110 +
b11110100 ,
b11000 -
b11 #
b11 (
b11 &
#21110
b11010100 $
#21200
b10100 !
b10100 )
b100000 -
b11110000 ,
b1000 +
b11111100 *
b100 #
b100 (
b100 &
#21210
b11010101 $
#21300
b11001 !
b11001 )
b11111011 *
b1010 +
b11101100 ,
b101000 -
b101 #
b101 (
b101 &
#21310
b11010110 $
#21400
b11110 !
b11110 )
b110000 -
b11101000 ,
b1100 +
b11111010 *
b110 #
b110 (
b110 &
#21410
b11010111 $
#21500
b100011 !
b100011 )
b11111001 *
b1110 +
b11100100 ,
b111000 -
b111 #
b111 (
b111 &
#21510
b11011000 $
#21600
b101000 !
b101000 )
b1000000 -
b11100000 ,
b10000 +
b11111000 *
b1000 #
b1000 (
b1000 &
#21610
b11011001 $
#21700
b101101 !
b101101 )
b11110111 *
b10010 +
b11011100 ,
b1001000 -
b1001 #
b1001 (
b1001 &
#21710
b11011010 $
#21800
b110010 !
b110010 )
b1010000 -
b11011000 ,
b10100 +
b11110110 *
b1010 #
b1010 (
b1010 &
#21810
b11011011 $
#21900
b110111 !
b110111 )
b11110101 *
b10110 +
b11010100 ,
b1011000 -
b1011 #
b1011 (
b1011 &
#21910
b11011100 $
#22000
b111100 !
b111100 )
b1100000 -
b11010000 ,
b11000 +
b11110100 *
b1100 #
b1100 (
b1100 &
#22010
b11011101 $
#22100
b1000001 !
b1000001 )
b11110011 *
b11010 +
b11001100 ,
b1101000 -
b1101 #
b1101 (
b1101 &
#22110
b11011110 $
#22200
b1000110 !
b1000110 )
b1110000 -
b11001000 ,
b11100 +
b11110010 *
b1110 #
b1110 (
b1110 &
#22210
b11011111 $
#22300
b1001011 !
b1001011 )
b11110001 *
b11110 +
b11000100 ,
b1111000 -
b1111 #
b1111 (
b1111 &
#22310
b11100000 $
#22400
b0 !
b0 )
b0 -
b0 ,
b0 +
b0 *
b0 #
b0 (
b110 "
b110 '
b110 %
b0 &
#22410
b11100001 $
#22500
b110 !
b110 )
b11111110 +
b1000 -
b1 #
b1 (
b1 &
#22510
b11100010 $
#22600
b1100 !
b1100 )
b10000 -
b11111100 +
b10 #
b10 (
b10 &
#22610
b11100011 $
#22700
b10010 !
b10010 )
b11111010 +
b11000 -
b11 #
b11 (
b11 &
#22710
b11100100 $
#22800
b11000 !
b11000 )
b100000 -
b11111000 +
b100 #
b100 (
b100 &
#22810
b11100101 $
#22900
b11110 !
b11110 )
b11110110 +
b101000 -
b101 #
b101 (
b101 &
#22910
b11100110 $
#23000
b100100 !
b100100 )
b110000 -
b11110100 +
b110 #
b110 (
b110 &
#23010
b11100111 $
